embree-vars.csh
embree-vars.sh
igl/__init__.py
igl/pyigl_core.cpython-39-aarch64-linux-gnu.so
igl/pyigl_core.pyi
igl/copyleft/__init__.py
igl/copyleft/pyigl_copyleft_core.cpython-39-aarch64-linux-gnu.so
igl/copyleft/pyigl_copyleft_core.pyi
igl/copyleft/cgal/__init__.py
igl/copyleft/cgal/pyigl_copyleft_cgal.cpython-39-aarch64-linux-gnu.so
igl/copyleft/cgal/pyigl_copyleft_cgal.pyi
igl/copyleft/tetgen/__init__.py
igl/copyleft/tetgen/pyigl_copyleft_tetgen.cpython-39-aarch64-linux-gnu.so
igl/copyleft/tetgen/pyigl_copyleft_tetgen.pyi
igl/embree/__init__.py
igl/embree/pyigl_embree.cpython-39-aarch64-linux-gnu.so
igl/embree/pyigl_embree.pyi
igl/triangle/__init__.py
igl/triangle/pyigl_restricted_triangle.cpython-39-aarch64-linux-gnu.so
igl/triangle/pyigl_restricted_triangle.pyi
include/Eigen/Cholesky
include/Eigen/CholmodSupport
include/Eigen/Core
include/Eigen/Dense
include/Eigen/Eigen
include/Eigen/Eigenvalues
include/Eigen/Geometry
include/Eigen/Householder
include/Eigen/IterativeLinearSolvers
include/Eigen/Jacobi
include/Eigen/KLUSupport
include/Eigen/LU
include/Eigen/MetisSupport
include/Eigen/OrderingMethods
include/Eigen/PaStiXSupport
include/Eigen/PardisoSupport
include/Eigen/QR
include/Eigen/QtAlignedMalloc
include/Eigen/SPQRSupport
include/Eigen/SVD
include/Eigen/Sparse
include/Eigen/SparseCholesky
include/Eigen/SparseCore
include/Eigen/SparseLU
include/Eigen/SparseQR
include/Eigen/StdDeque
include/Eigen/StdList
include/Eigen/StdVector
include/Eigen/SuperLUSupport
include/Eigen/UmfPackSupport
include/Eigen/src/Cholesky/LDLT.h
include/Eigen/src/Cholesky/LLT.h
include/Eigen/src/Cholesky/LLT_LAPACKE.h
include/Eigen/src/CholmodSupport/CholmodSupport.h
include/Eigen/src/Core/ArithmeticSequence.h
include/Eigen/src/Core/Array.h
include/Eigen/src/Core/ArrayBase.h
include/Eigen/src/Core/ArrayWrapper.h
include/Eigen/src/Core/Assign.h
include/Eigen/src/Core/AssignEvaluator.h
include/Eigen/src/Core/Assign_MKL.h
libigl-2.6.1.dist-info/METADATA
libigl-2.6.1.dist-info/WHEEL
libigl-2.6.1.dist-info/RECORD
libigl-2.6.1.dist-info/licenses/LICENSE.GPL
libigl-2.6.1.dist-info/licenses/LICENSE.MPL2
