Metadata-Version: 2.1
Name: libigl
Version: 2.6.1
Summary: libigl: A simple C++ geometry processing library
Author-Email: Alec Jacobson <alecjacobson@gmail.com>
Classifier: License :: OSI Approved :: Mozilla Public License 2.0 (MPL 2.0)
Project-URL: Homepage, https://github.com/libigl/libigl-python-bindings
Requires-Python: >=3.8
Requires-Dist: numpy
Requires-Dist: scipy
